joystick/__init__.py
joystick/_async/__init__.py
joystick/_async/cache_key_builder.py
joystick/_async/client.py
joystick/_async/params_dict.py
joystick/_async/transport.py
joystick/_async/cache/__init__.py
joystick/_async/cache/cache.py
joystick/_async/cache/in_memory.py
joystick/_sync/README.md
joystick/_sync/__init__.py
joystick/_sync/cache_key_builder.py
joystick/_sync/client.py
joystick/_sync/params_dict.py
joystick/_sync/transport.py
joystick/_sync/cache/__init__.py
joystick/_sync/cache/cache.py
joystick/_sync/cache/in_memory.py
joystick/errors/__init__.py
joystick/errors/joystick_error.py
joystick/errors/api/__init__.py
joystick_python-0.1.0a1.dist-info/LICENSE.md
joystick_python-0.1.0a1.dist-info/METADATA
joystick_python-0.1.0a1.dist-info/WHEEL
joystick_python-0.1.0a1.dist-info/top_level.txt
joystick_python-0.1.0a1.dist-info/RECORD
