Metadata-Version: 2.1
Name: joystick-python
Version: 0.1.0a1
Summary: Joystick is a modern remote configuration and dynamic content service designed specifically for operating apps and games. Upgrade to more agility and evolve your product faster. Change or hot-update your content and configurations instantly at scale without code. Segment, ab test, feature flag, schedule events and more. Joystick is a breeze to use yet powerful.
Home-page: https://github.com/getjoystick/getjoystick/joystick-python
Author: Joystick
Author-email: letsgo@getjoystick.com
License: MIT
Project-URL: Changelog, https://github.com/getjoystick/joystick-python/blob/main/CHANGELOG.md
Project-URL: Issue Tracker, https://github.com/getjoystick/joystick-python/issues
Keywords: Remote configuration,feature flagging,dynamic content,remote configs,live-ops,game ops,ab testing,segmentation,dynamic json,update json,remote json
Classifier: Development Status :: 5 - Production/Stable
Classifier: Intended Audience :: Developers
Classifier: License :: OSI Approved :: MIT License
Classifier: Operating System :: Unix
Classifier: Operating System :: POSIX
Classifier: Operating System :: Microsoft :: Windows
Classifier: Programming Language :: Python
Classifier: Programming Language :: Python :: 3
Classifier: Programming Language :: Python :: 3 :: Only
Classifier: Programming Language :: Python :: 3.7
Classifier: Programming Language :: Python :: 3.8
Classifier: Programming Language :: Python :: 3.9
Classifier: Programming Language :: Python :: 3.10
Classifier: Programming Language :: Python :: 3.11
Classifier: Programming Language :: Python :: Implementation :: CPython
Classifier: Programming Language :: Python :: Implementation :: PyPy
Classifier: Topic :: Utilities
Requires-Python: >=3.6
License-File: LICENSE.md
Requires-Dist: httpx[http2] (<1.0,>=0.23.3)
Requires-Dist: pylru (<2.0.0,>=1.2.1)
Provides-Extra: dev
Requires-Dist: nox ; extra == 'dev'
Requires-Dist: wheel ; extra == 'dev'
